nock_kernel/__init__.py
nock_kernel/kernel.py
nock_kernel/kernelspec/kernel.json
nock_kernel-1.2.1.dist-info/METADATA
nock_kernel-1.2.1.dist-info/WHEEL
nock_kernel-1.2.1.dist-info/top_level.txt
nock_kernel-1.2.1.dist-info/RECORD
