Metadata-Version: 2.4
Name: nock_kernel
Version: 1.2.1
Summary: Jupyter kernel for interactive Nock evaluation.
Home-page: https://github.com/sigilante/pinochle
Author: N. E. Davis
Author-email: "N. E. Davis" <neal@zorp.io>
License: MIT
Project-URL: Homepage, https://github.com/sigilante/pinochle
Project-URL: Repository, https://github.com/sigilante/pinochle
Project-URL: Issues, https://github.com/sigilante/pinochle/issues
Keywords: nock,urbit,interpreter,pinochle,nockapp,nockchain
Classifier: Development Status :: 4 - Beta
Classifier: Intended Audience :: Developers
Classifier: License :: OSI Approved :: MIT License
Classifier: Programming Language :: Python :: 3
Classifier: Programming Language :: Python :: 3.8
Classifier: Programming Language :: Python :: 3.9
Classifier: Programming Language :: Python :: 3.10
Classifier: Programming Language :: Python :: 3.11
Classifier: Programming Language :: Python :: 3.12
Classifier: Topic :: Software Development :: Interpreters
Requires-Python: >=3.8
Requires-Dist: mmh3
Requires-Dist: bitstring
Dynamic: author
Dynamic: home-page
Dynamic: requires-python
